Metadata-Version: 2.1
Name: ql-orange
Version: 1.4.0
Summary: Orange is a fork of Black Python code formatter maintained by Quantlane.
Home-page: https://gitlab.com/quantlane/meta/orange
Author: quantlane.com
Author-email: info@quantlane.com
Requires-Python: >=3.7,<4.0
Classifier: Programming Language :: Python :: 3
Classifier: Programming Language :: Python :: 3.10
Classifier: Programming Language :: Python :: 3.7
Classifier: Programming Language :: Python :: 3.8
Classifier: Programming Language :: Python :: 3.9
Provides-Extra: d
Provides-Extra: jupyter
Requires-Dist: aiohttp (>=3.7.4); extra == "d"
Requires-Dist: click (>=8.0.0)
Requires-Dist: ipython (>=7.8.0); extra == "jupyter"
Requires-Dist: mypy_extensions (>=0.4.3)
Requires-Dist: pathspec (>=0.9.0)
Requires-Dist: platformdirs (>=2)
Requires-Dist: tokenize-rt (>=3.2.0); extra == "jupyter"
Requires-Dist: tomli (>=1.1.0)
Requires-Dist: typed-ast (>=1.4.2); python_version < "3.8"
Requires-Dist: typing_extensions (>=3.10.0.0); python_version < "3.10"
Project-URL: Repository, https://gitlab.com/quantlane/meta/orange
